pyimpsort.py
pyimpsort-0.1.1.dist-info/licenses/LICENSE-MIT
pyimpsort-0.1.1.dist-info/METADATA
pyimpsort-0.1.1.dist-info/WHEEL
pyimpsort-0.1.1.dist-info/entry_points.txt
pyimpsort-0.1.1.dist-info/top_level.txt
pyimpsort-0.1.1.dist-info/RECORD
