Metadata-Version: 2.4
Name: pyimpsort
Version: 0.1.1
Summary: Sort Python import statements.
Maintainer-email: Alain Delplanque <alaindelplanque@mailoo.org>
License: MIT License
Project-URL: Homepage, https://github.com/emacsorphanage/pyimpsort
Project-URL: Repository, https://github.com/emacsorphanage/pyimpsort
Project-URL: Issues, https://github.com/emacsorphanage/pyimpsort/issues
Keywords: imports,formatter,python,emacs
Classifier: Development Status :: 4 - Beta
Classifier: Intended Audience :: Developers
Classifier: Natural Language :: English
Classifier: Programming Language :: Python :: 3
Classifier: Programming Language :: Python :: 3.6
Classifier: Programming Language :: Python :: 3.7
Classifier: Programming Language :: Python :: 3.8
Classifier: Programming Language :: Python :: 3.9
Classifier: Programming Language :: Python :: 3.10
Classifier: Programming Language :: Python :: 3.11
Classifier: Programming Language :: Python :: 3.12
Classifier: Programming Language :: Python :: 3.13
Classifier: Topic :: Utilities
Classifier: Environment :: Console
Requires-Python: >=3.6
License-File: LICENSE-MIT
Dynamic: license-file
